{
	"name": "pl_ctrl_start",
	"properties": {
		"activities": [
			{
				"name": "lkp_sp_start",
				"type": "Lookup",
				"dependsOn": [],
				"policy": {
					"timeout": "0.12:00:00",
					"retry": 0,
					"retryIntervalInSeconds": 30,
					"secureOutput": false,
					"secureInput": false
				},
				"userProperties": [],
				"typeProperties": {
					"source": {
						"type": "AzureSqlSource",
						"sqlReaderStoredProcedureName": "[dbo].[sp_log_start]",
						"storedProcedureParameters": {
							"execution_id": {
								"type": "Guid"
							},
							"pipeline_name": {
								"type": "String"
							},
							"pipeline_type": {
								"type": "String"
							},
							"PipelineId": {
								"type": "Int32"
							}
						},
						"queryTimeout": "02:00:00",
						"partitionOption": "None"
					},
					"dataset": {
						"referenceName": "ds_sql_generic",
						"type": "DatasetReference",
						"parameters": {
							"TableName": {
								"value": "@pipeline().parameters.TablaParametro",
								"type": "Expression"
							},
							"SchemaName": "dbo"
						}
					}
				}
			},
			{
				"name": "Set_IdEjecucion",
				"type": "SetVariable",
				"dependsOn": [
					{
						"activity": "lkp_sp_start",
						"dependencyConditions": [
							"Succeeded"
						]
					}
				],
				"policy": {
					"secureOutput": false,
					"secureInput": false
				},
				"userProperties": [],
				"typeProperties": {
					"variableName": "pipelineReturnValue",
					"value": [
						{
							"key": "IdEjecucion",
							"value": {
								"type": "Expression",
								"content": "@activity('lkp_sp_start').output.firstRow.IdEjecucion"
							}
						}
					],
					"setSystemVariable": true
				}
			}
		],
		"parameters": {
			"PipelineId": {
				"type": "int"
			},
			"TablaParametro": {
				"type": "string"
			},
			"ExecutionId": {
				"type": "string"
			},
			"pipeline_name": {
				"type": "string"
			},
			"pipeline_type": {
				"type": "string"
			}
		},
		"variables": {
			"IdEjecucion": {
				"type": "Integer"
			}
		},
		"annotations": []
	}
}